README.md
setup.cfg
setup.py
broker_json/__init__.py
broker_json/conversions.py
broker_json/find_broker.py
broker_json/utils.py
broker_json.egg-info/PKG-INFO
broker_json.egg-info/SOURCES.txt
broker_json.egg-info/dependency_links.txt
broker_json.egg-info/top_level.txt
broker_json/tests/__init__.py
broker_json/tests/test_broker_conversions.py